LICENSE
MANIFEST.in
README.md
setup.py
extract_specific_lines/__init__.py
extract_specific_lines/extract_specific_lines.py
extract_specific_lines.egg-info/PKG-INFO
extract_specific_lines.egg-info/SOURCES.txt
extract_specific_lines.egg-info/dependency_links.txt
extract_specific_lines.egg-info/entry_points.txt
extract_specific_lines.egg-info/top_level.txt