Metadata-Version: 2.1
Name: extract-specific-lines
Version: 0.0.3
Summary: to get specific lines from the subject file which maps the query ids. Written by Guanliang MENG
Home-page: https://github.com/linzhi2013/extract_specific_lines
Author: Guanliang Meng
Author-email: linzhi2012@gmail.com
License: UNKNOWN
Platform: UNKNOWN
Classifier: Development Status :: 3 - Alpha
Classifier: Intended Audience :: Science/Research
Classifier: Topic :: Scientific/Engineering :: Bio-Informatics
Classifier: License :: OSI Approved :: GNU General Public License v3 or later (GPLv3+)
Classifier: Programming Language :: Python :: 3
Classifier: Operating System :: MacOS :: MacOS X
Classifier: Operating System :: Microsoft :: Windows
Classifier: Operating System :: POSIX :: Linux
Requires-Python: >=3
